CONTRIBUTORS
INSTALL
LICENSE
MANIFEST.in
Makefile
README.rst
ez_setup.py
run_all_examples.py
run_examples.py
setup.py
should_dsl/__init__.py
should_dsl/backwardscompat.py
should_dsl/dsl.py
should_dsl/matchers.py
should_dsl.egg-info/PKG-INFO
should_dsl.egg-info/SOURCES.txt
should_dsl.egg-info/dependency_links.txt
should_dsl.egg-info/top_level.txt