Metadata-Version: 1.0
Name: should-dsl
Version: 2.1
Summary: Should assertions in Python as clear and readable as possible
Home-page: www.should-dsl.info
Author: Hugo Lopes Tavares
Author-email: hltbra@gmail.com
License: MIT License
Keywords: should dsl assertion bdd python expectation
Platform: UNKNOWN
Classifier: Development Status :: 3 - Alpha
Classifier: Intended Audience :: Developers
Classifier: License :: OSI Approved :: MIT License
Classifier: Programming Language :: Python
Classifier: Programming Language :: Python :: 2
Classifier: Programming Language :: Python :: 2.4
Classifier: Programming Language :: Python :: 2.5
Classifier: Programming Language :: Python :: 2.6
Classifier: Programming Language :: Python :: 3
Classifier: Programming Language :: Python :: 3.2
Classifier: Topic :: Software Development :: Documentation
Classifier: Topic :: Software Development :: Libraries
Classifier: Topic :: Software Development :: Testing
